core/__init__.py
core/asgi.py
core/settings.py
core/urls.py
core/wsgi.py
custom_auth/__init__.py
custom_auth/admin.py
custom_auth/apps.py
custom_auth/models.py
custom_auth/serializers.py
custom_auth/token_authentication.py
custom_auth/urls.py
custom_auth/views.py
custom_auth/migrations/0001_initial.py
custom_auth/migrations/__init__.py
custom_auth/tests/__init__.py
custom_auth/tests/test_models.py
custom_auth/tests/test_views.py
django_auth_package-0.1.0.dist-info/licenses/LICENSE
django_auth_package-0.1.0.dist-info/METADATA
django_auth_package-0.1.0.dist-info/WHEEL
django_auth_package-0.1.0.dist-info/top_level.txt
django_auth_package-0.1.0.dist-info/RECORD
